aniparse/__init__.py
aniparse/aniparse.py
aniparse/element.py
aniparse/keyword.py
aniparse/parser.py
aniparse/parser_helper.py
aniparse/parser_number.py
aniparse/token.py
aniparse/tokenizer.py
tests/__init__.py
tests/test_aniparse.py
tests/fixtures/__init__.py
tests/fixtures/table.py
aniparse-1.2.2.dist-info/LICENSE
aniparse-1.2.2.dist-info/METADATA
aniparse-1.2.2.dist-info/WHEEL
aniparse-1.2.2.dist-info/top_level.txt
aniparse-1.2.2.dist-info/RECORD
