Metadata-Version: 2.1
Name: aniparse
Version: 1.2.2
Summary: An anime video filename parser
Home-page: https://github.com/MeGaNeKoS/aniparse
Author: めがねこ
Author-email: evictory91+pypackages@gmail.com
License: License :: OSI Approved :: Mozilla Public License 2.0 (MPL 2.0)
Keywords: anime,filename parser
Classifier: Development Status :: 5 - Production/Stable
Classifier: Intended Audience :: Developers
Classifier: Programming Language :: Python :: 3
Classifier: Programming Language :: Python :: 3.6
Classifier: Programming Language :: Python :: 3.7
Classifier: Programming Language :: Python :: 3.8
Classifier: Programming Language :: Python :: 3.9
Classifier: Programming Language :: Python :: 3.10
Classifier: Programming Language :: Python :: 3.11
License-File: LICENSE
